{"items":[{"id":null,"type":"Ip","filePath":"cmd/kubeadm/app/util/pkiutil/pki_helpers_test.go","language":"Go","finding":"10.10.10.100","lineContent":"\tproxyIP := \"10.10.10.100\"","line":775,"column":14},{"id":null,"type":"File","filePath":"pkg/volume/cinder/attacher_test.go","language":"Go","finding":"\"/var/lib/kubelet/\"","lineContent":"\trootDir := \"/var/lib/kubelet/\"","line":79,"column":13},{"id":null,"type":"Domain","filePath":"cmd/kubeadm/app/cmd/init.go","language":"Go","finding":"","lineContent":"\t\t  https://kubernetes.io/docs/concepts/cluster-administration/addons/","line":65,"column":1},{"id":null,"type":"ApiKey","filePath":"staging/src/k8s.io/client-go/plugin/pkg/client/auth/gcp/gcp_test.go","language":"Go","finding":"Token: \"faketoken\",","lineContent":"\t\t\t\tAccessToken: \"faketoken\",","line":330,"column":11},{"id":null,"type":"UserId","filePath":"pkg/serviceaccount/claims_test.go","language":"Go","finding":"UID:       \"mysvcacct-uid\",","lineContent":"\t\t\tUID:       \"mysvcacct-uid\",","line":47,"column":4},{"id":null,"type":"Password","filePath":"staging/src/k8s.io/kubectl/pkg/generate/versioned/secret_for_docker_registry_test.go","language":"Go","finding":"server := \"test-user\", \"test-password\", \"test-user@example.org\", \"https://index.docker.io/v1/\"","lineContent":"\tusername, password, email, server := \"test-user\", \"test-password\", \"test-user@example.org\", \"https://index.docker.io/v1/\"","line":29,"column":29},{"id":null,"type":"PrivateKey","filePath":"staging/src/k8s.io/apiserver/pkg/util/webhook/certs_test.go","language":"Go","finding":"-----BEGIN RSA PRIVATE KEY-----","lineContent":"var serverKey = []byte(`-----BEGIN RSA PRIVATE KEY-----","line":120,"column":25},{"id":null,"type":"Ip","filePath":"pkg/proxy/ipvs/proxier_test.go","language":"Go","finding":"10.180.0.1","lineContent":"\t\t\t\t\t\t\tIP: \"10.180.0.1\",","line":492,"column":13},{"id":null,"type":"File","filePath":"pkg/volume/util/nested_volumes_test.go","language":"Go","finding":"\"/mnt/sub1/sub2/sub6\", Name: \"vol6\"","lineContent":"\t\t\t\t\t\t\t\t{MountPath: \"/mnt/sub1/sub2/sub6\", Name: \"vol6\"},","line":160,"column":21},{"id":null,"type":"Domain","filePath":"cluster/gce/config-test.sh","language":"Bourne Shell","finding":"","lineContent":"PROMETHEUS_TO_SD_ENDPOINT=${PROMETHEUS_TO_SD_ENDPOINT:-https://monitoring.googleapis.com/}","line":528,"column":1}],"paging":null}