{"items":[{"id":null,"type":"Ip","filePath":"test/units/module_utils/facts/network/test_generic_bsd.py","language":"Python","finding":"192.168.122.205","lineContent":"'ipv4': [{'address': '192.168.122.205',","line":89,"column":23},{"id":null,"type":"File","filePath":"lib/ansible/module_utils/urls.py","language":"Python","finding":"'/etc/ssl/certs'","lineContent":"paths_checked.append('/etc/ssl/certs')","line":929,"column":22},{"id":null,"type":"Domain","filePath":"test/lib/ansible_test/_internal/ci/shippable.py","language":"Python","finding":"","lineContent":"url = 'https://api.shippable.com/runs?%s' % urlencode(parameters)","line":249,"column":1},{"id":null,"type":"ApiKey","filePath":"lib/ansible/modules/apt_repository.py","language":"Python","finding":"API = 'https://launchpad.net/api/1.0/~%s/+archive/%s'","lineContent":"LP_API = 'https://launchpad.net/api/1.0/~%s/+archive/%s'","line":421,"column":4},{"id":null,"type":"UserId","filePath":"test/lib/ansible_test/_internal/core_ci.py","language":"Python","finding":"username='username',","lineContent":"username='username',","line":276,"column":1},{"id":null,"type":"Password","filePath":"test/lib/ansible_test/_internal/cloud/nios.py","language":"Python","finding":"password='infoblox',","lineContent":"password='infoblox',","line":187,"column":1},{"id":null,"type":"Ip","filePath":"test/units/module_utils/facts/network/test_generic_bsd.py","language":"Python","finding":"192.168.122.205","lineContent":"NETBSD_EXPECTED = {'all_ipv4_addresses': ['192.168.122.205'],","line":71,"column":44},{"id":null,"type":"File","filePath":"lib/ansible/module_utils/urls.py","language":"Python","finding":"'/etc/pki/ca-trust/extracted/pem'","lineContent":"paths_checked.append('/etc/pki/ca-trust/extracted/pem')","line":935,"column":22},{"id":null,"type":"Domain","filePath":"lib/ansible/module_utils/urls.py","language":"Python","finding":"","lineContent":"url='https://pypi.org/project/gssapi/')","line":1340,"column":1},{"id":null,"type":"ApiKey","filePath":"test/units/executor/test_task_executor.py","language":"Python","finding":"token = 'POPCORN'","lineContent":"omit_token = 'POPCORN'","line":429,"column":6}],"paging":null}