{"items":[{"id":null,"type":"Ip","filePath":"pkg/controller/nodeipam/ipam/cidrset/cidr_set_test.go","language":"Go","finding":"10.42.4.0","lineContent":"\t\t\tcidrStr:     \"10.42.4.0/22\",","line":393,"column":18},{"id":null,"type":"File","filePath":"pkg/security/apparmor/validate_test.go","language":"Go","finding":"\"/usr/sbin/ntpd\"","lineContent":"\t\t\"/usr/sbin/ntpd\": true,","line":55,"column":3},{"id":null,"type":"Domain","filePath":"test/e2e/kubectl/kubectl.go","language":"Go","finding":"","lineContent":"\t\t\tgomega.Expect(execOutput).To(gomega.ContainSubstring(\"GET https://kubernetes.default.svc:443/api/v1/namespaces/default/pods\"))","line":767,"column":1},{"id":null,"type":"ApiKey","filePath":"staging/src/k8s.io/apiserver/plugin/pkg/authenticator/token/webhook/webhook_v1_test.go","language":"Go","finding":"token: \"an0th3r_t0k3n\",","lineContent":"\t\t\ttoken: \"an0th3r_t0k3n\",","line":641,"column":4},{"id":null,"type":"UserId","filePath":"test/integration/certificates/admission_sign_test.go","language":"Go","finding":"username = \"test-user\"","lineContent":"\t\t\tconst username = \"test-user\"","line":64,"column":10},{"id":null,"type":"Password","filePath":"staging/src/k8s.io/kubectl/pkg/cmd/testing/fake.go","language":"Go","finding":"Server: \"http://localhost:8080\"","lineContent":"\toverrides := &clientcmd.ConfigOverrides{ClusterDefaults: clientcmdapi.Cluster{Server: \"http://localhost:8080\"}}","line":417,"column":80},{"id":null,"type":"PrivateKey","filePath":"test/integration/apiserver/admissionwebhook/admission_test.go","language":"Go","finding":"-----BEGIN RSA PRIVATE KEY-----","lineContent":"var localhostKey = []byte(`-----BEGIN RSA PRIVATE KEY-----","line":1676,"column":28},{"id":null,"type":"Ip","filePath":"pkg/apis/core/validation/validation.go","language":"Go","finding":"169.254.0.0","lineContent":"\t\tallErrs = append(allErrs, field.Invalid(fldPath, ipAddress, \"may not be in the link-local range (169.254.0.0/16)\"))","line":5729,"column":100},{"id":null,"type":"File","filePath":"pkg/security/apparmor/validate_test.go","language":"Go","finding":"\"/usr/lib/connman/scripts/dhclient-script\"","lineContent":"\t\t\"/usr/lib/connman/scripts/dhclient-script\":      true,","line":56,"column":3},{"id":null,"type":"Domain","filePath":"test/e2e/kubectl/kubectl.go","language":"Go","finding":"","lineContent":"server: https://kubernetes.default.svc:443","line":687,"column":1}],"paging":null}