{"items":[{"id":null,"type":"Ip","filePath":"modules/ssh/src/test/java/org/apache/ignite/internal/IgniteNodeStartUtilsSelfTest.java","language":"Java","finding":"192.168.1.1","lineContent":"assert \"192.168.1.1\".equals(host.get(HOST)) || \"192.168.1.2\".equals(host.get(HOST));","line":62,"column":9},{"id":null,"type":"File","filePath":"modules/core/src/test/java/org/apache/ignite/internal/sql/SqlParserBulkLoadSelfTest.java","language":"Java","finding":"'d:/copy/from/into/format.csv' into Person (_key, age, firstName, lastName) format csv\"","lineContent":"\"copy from 'd:/copy/from/into/format.csv' into Person (_key, age, firstName, lastName) format csv\")","line":50,"column":12},{"id":null,"type":"Domain","filePath":"bin/ignite.bat","language":"DOS Batch","finding":"","lineContent":"echo You can also download latest JDK at http://java.com/download.","line":62,"column":1},{"id":null,"type":"ApiKey","filePath":"modules/core/src/main/java/org/apache/ignite/internal/processors/odbc/odbc/escape/OdbcEscapeUtils.java","language":"Java","finding":"token=\" + token.type().body() + ']'","lineContent":"substring(text, startPos, len) + \", token=\" + token.type().body() + ']');","line":289,"column":37},{"id":null,"type":"UserId","filePath":"examples/src/main/java/org/apache/ignite/examples/computegrid/ComputeBroadcastExample.java","language":"Java","finding":"User: \" + System.getProperty(\"user.name\") + \"\\n\"","lineContent":"\"User: \" + System.getProperty(\"user.name\") + \"\\n\" +","line":87,"column":2},{"id":null,"type":"Password","filePath":"modules/rest-http/src/main/java/org/apache/ignite/internal/processors/rest/protocols/http/jetty/GridJettyRestHandler.java","language":"Java","finding":"PASSWORD = \"ignite.password\";","lineContent":"private static final String IGNITE_PASSWORD = \"ignite.password\";","line":132,"column":36},{"id":null,"type":"Ip","filePath":"modules/ssh/src/test/java/org/apache/ignite/internal/IgniteNodeStartUtilsSelfTest.java","language":"Java","finding":"192.168.1.2","lineContent":"assert \"192.168.1.1\".equals(host.get(HOST)) || \"192.168.1.2\".equals(host.get(HOST));","line":62,"column":49},{"id":null,"type":"File","filePath":"modules/visor-console/src/main/scala/org/apache/ignite/visor/commands/vvm/VisorVvmCommand.scala","language":"Scala","finding":"'C:\\\\VisualVM' folder for specified node.\"","lineContent":"\"Opens VisualVM installed in 'C:\\\\VisualVM' folder for specified node.\",","line":282,"column":30},{"id":null,"type":"Domain","filePath":"bin/ignite.bat","language":"DOS Batch","finding":"","lineContent":"echo You can also download latest JDK at http://java.com/download.","line":41,"column":1},{"id":null,"type":"ApiKey","filePath":"modules/kubernetes/src/main/java/org/apache/ignite/kubernetes/configuration/KubernetesConnectionConfiguration.java","language":"Java","finding":"Token = \"/var/run/secrets/kubernetes.io/serviceaccount/token\";","lineContent":"private String accountToken = \"/var/run/secrets/kubernetes.io/serviceaccount/token\";","line":36,"column":23}],"paging":null}