{"items":[{"id":null,"type":"Ip","filePath":"galley/pkg/config/testing/data/builtin.gen.go","language":"Go","finding":"10.128.0.5","lineContent":"hostIP: 10.128.0.5","line":712,"column":9},{"id":null,"type":"File","filePath":"pilot/pkg/xds/xds_test.go","language":"Go","finding":"\"/var/run/someuds.sock\"","lineContent":"\t\tif !listEqualUnordered(eps, []string{\"/var/run/someuds.sock\"}) {","line":216,"column":40},{"id":null,"type":"Domain","filePath":"galley/pkg/config/testing/data/builtin.gen.go","language":"Go","finding":"","lineContent":"- --api-override=https://monitoring.googleapis.com/","line":596,"column":1},{"id":null,"type":"ApiKey","filePath":"security/pkg/stsservice/test/setup.go","language":"Go","finding":"Token = \"thisisafakejwt\"","lineContent":"\tjwtToken = \"thisisafakejwt\"","line":42,"column":5},{"id":null,"type":"UserId","filePath":"pkg/config/security/security.go","language":"Go","finding":"User         = \"destination.user\"       // service account, e.g. \"bookinfo-productpage\"","lineContent":"\tattrDestUser         = \"destination.user\"       // service account, e.g. \"bookinfo-productpage\".","line":52,"column":10},{"id":null,"type":"Password","filePath":"pkg/errdict/errdict.go","language":"Go","finding":"Server     = \"a problem with the Kubernetes API server\"","lineContent":"\tLikelyCauseAPIServer     = \"a problem with the Kubernetes API server\"","line":38,"column":16},{"id":null,"type":"PrivateKey","filePath":"tests/integration/security/sds_ingress/util/test_certs.go","language":"Go","finding":"-----BEGIN RSA PRIVATE KEY-----","lineContent":"\tTLSServerKeyA = `-----BEGIN RSA PRIVATE KEY-----","line":45,"column":19},{"id":null,"type":"Ip","filePath":"galley/pkg/config/testing/data/builtin.gen.go","language":"Go","finding":"10.40.1.4","lineContent":"podIP: 10.40.1.4","line":714,"column":8},{"id":null,"type":"File","filePath":"pilot/pkg/xds/filters/filters.go","language":"Go","finding":"\"/etc/istio/extensions/metadata-exchange-filter.compiled.wasm\"","lineContent":"\t\t\t\t\t\t\tFilename: \"/etc/istio/extensions/metadata-exchange-filter.compiled.wasm\",","line":182,"column":18},{"id":null,"type":"Domain","filePath":"security/pkg/stsservice/tokenmanager/google/tokenexchangeplugin.go","language":"Go","finding":"","lineContent":"\taccessTokenEndpoint    = \"https://iamcredentials.googleapis.com/v1/projects/-/\" +","line":52,"column":1}],"paging":null}