{"items":[{"id":null,"type":"Ip","filePath":"src/Middleware/HttpOverrides/test/IPNetworkTest.cs","language":"C#","finding":"10.174.0.0","lineContent":"[InlineData(\"10.174.0.0\", 15, \"10.173.1.10\")]","line":24,"column":14},{"id":null,"type":"File","filePath":"src/Razor/Microsoft.AspNetCore.Razor.Language/test/DefaultRazorProjectFileSystemTest.cs","language":"C#","finding":"\"C:/some/test/path/root/something/file.cshtml\"","lineContent":"Assert.Equal(\"C:/some/test/path/root/something/file.cshtml\", absolutePath);","line":93,"column":14},{"id":null,"type":"Domain","filePath":"eng/common/post-build/add-build-to-channel.ps1","language":"PowerShell","finding":"","lineContent":"[Parameter(Mandatory=$false)][string] $MaestroApiEndPoint = 'https://maestro-prod.westus2.cloudapp.azure.com',","line":5,"column":1},{"id":null,"type":"ApiKey","filePath":"src/SignalR/clients/csharp/Client/test/UnitTests/ResponseUtils.cs","language":"C#","finding":"Token = \"connection-token\",","lineContent":"HttpTransportType? transportTypes = null, string connectionToken = \"connection-token\", int negotiateVersion = 0)","line":65,"column":60},{"id":null,"type":"UserId","filePath":"src/Identity/test/Identity.Test/UserClaimsPrincipalFactoryTest.cs","language":"C#","finding":"UserName = \"Foo\", Email = \"foo@bar.com\"","lineContent":"var user = new PocoUser { UserName = \"Foo\", Email = \"foo@bar.com\" };","line":50,"column":27},{"id":null,"type":"Password","filePath":"src/Identity/test/InMemory.Test/ControllerTest.cs","language":"C#","finding":"password = \"Yol0Sw@g!\";","lineContent":"const string password = \"Yol0Sw@g!\";","line":49,"column":14},{"id":null,"type":"Ip","filePath":"src/Middleware/HttpOverrides/test/IPNetworkTest.cs","language":"C#","finding":"10.171.1.10","lineContent":"[InlineData(\"10.168.0.0\", 14, \"10.171.1.10\")]","line":14,"column":32},{"id":null,"type":"File","filePath":"src/Razor/Microsoft.AspNetCore.Razor.Language/test/DefaultRazorProjectFileSystemTest.cs","language":"C#","finding":"\"C:\\some\\test\\path\\root\"","lineContent":"var fileSystem = new TestRazorProjectFileSystem(@\"C:\\some\\test\\path\\root\");","line":87,"column":50},{"id":null,"type":"Domain","filePath":"src/Mvc/Mvc.Core/src/DependencyInjection/MvcCoreMvcBuilderExtensions.cs","language":"C#","finding":"","lineContent":"UrlFormat = \"https://aka.ms/aspnetcore-warnings/{0}\")]","line":183,"column":1},{"id":null,"type":"ApiKey","filePath":"src/Security/Authentication/test/GoogleTests.cs","language":"C#","finding":"token = \"Test Refresh Token\"","lineContent":"refresh_token = \"Test Refresh Token\"","line":1030,"column":9}],"paging":null}