{"paging":null,"issues":[{"id":null,"file":"UITests/numberedPage.html","type":"Bug","message":"Insert a <!DOCTYPE> declaration to before this <html> tag.","severity":"Major","line":1},{"id":null,"file":"taskcluster/scripts/bitrise-schedule.py","type":"Code Smell","message":"Replace this generic exception class with a more specific one.","severity":"Major","line":129},{"id":null,"file":"UITests/numberedPage.html","type":"Bug","message":"Add \"lang\" and/or \"xml:lang\" attributes to this \"<html>\" element","severity":"Major","line":1},{"id":null,"file":"Client/Frontend/UserContent/UserScripts/AllFrames/AtDocumentStart/DownloadHelper.js","type":"Code Smell","message":"'url' is already declared in the upper scope.","severity":"Major","line":17},{"id":null,"file":"Client/Assets/NetError.html","type":"Bug","message":"Add \"lang\" and/or \"xml:lang\" attributes to this \"<html>\" element","severity":"Major","line":5},{"id":null,"file":"Client/Frontend/UserContent/UserScripts/AllFrames/AtDocumentStart/DownloadHelper.js","type":"Code Smell","message":"Remove unused function 'getLastPathComponent'.","severity":"Minor","line":17},{"id":null,"file":"Client/Assets/NetError.html","type":"Bug","message":"Insert a <!DOCTYPE> declaration to before this <html> tag.","severity":"Major","line":5},{"id":null,"file":"Client/Frontend/UserContent/UserScripts/MainFrame/AtDocumentStart/NightModeHelper.js","type":"Code Smell","message":"'styleElement' is already declared in the upper scope.","severity":"Major","line":84},{"id":null,"file":"UITests/navigationDelegate.html","type":"Bug","message":"Add \"lang\" and/or \"xml:lang\" attributes to this \"<html>\" element","severity":"Major","line":1},{"id":null,"file":"Client/Frontend/UserContent/UserScripts/MainFrame/AtDocumentStart/NoImageModeHelper.js","type":"Code Smell","message":"'style' is already declared in the upper scope.","severity":"Major","line":67}]}