{"paging":null,"issues":[{"id":null,"file":"staging/src/k8s.io/apimachinery/pkg/conversion/helper_test.go","type":"Bug","message":"Remove this conditional structure or edit its code blocks so that they're not all the same.","severity":"Major","line":23},{"id":null,"file":"staging/src/k8s.io/mount-utils/mount_linux.go","type":"Code Smell","message":"This function has 9 parameters, which is greater than the 7 authorized.","severity":"Major","line":136},{"id":null,"file":"staging/src/k8s.io/apimachinery/pkg/runtime/converter.go","type":"Bug","message":"Remove this conditional structure or edit its code blocks so that they're not all the same.","severity":"Major","line":596},{"id":null,"file":"staging/src/k8s.io/mount-utils/mount_linux.go","type":"Code Smell","message":"Refactor this method to reduce its Cognitive Complexity from 28 to the 15 allowed.","severity":"Critical","line":360},{"id":null,"file":"staging/src/k8s.io/apimachinery/pkg/runtime/converter.go","type":"Bug","message":"Remove this conditional structure or edit its code blocks so that they're not all the same.","severity":"Major","line":538},{"id":null,"file":"staging/src/k8s.io/mount-utils/mount_linux.go","type":"Code Smell","message":"Define a constant instead of duplicating this literal \"unmount failed: %v\\nUnmounting arguments: %s\\nOutput: %s\" 3 times.","severity":"Critical","line":270},{"id":null,"file":"staging/src/k8s.io/code-generator/cmd/prerelease-lifecycle-gen/prerelease-lifecycle-generators/status.go","type":"Bug","message":"Remove this conditional structure or edit its code blocks so that they're not all the same.","severity":"Major","line":166},{"id":null,"file":"staging/src/k8s.io/mount-utils/mount_linux.go","type":"Code Smell","message":"Define a constant instead of duplicating this literal \"systemd-run\" 3 times.","severity":"Critical","line":167},{"id":null,"file":"staging/src/k8s.io/apiextensions-apiserver/pkg/apiserver/schema/objectmeta/coerce_test.go","type":"Bug","message":"Remove this conditional structure or edit its code blocks so that they're not all the same.","severity":"Major","line":130},{"id":null,"file":"staging/src/k8s.io/mount-utils/mount_linux.go","type":"Code Smell","message":"Define a constant instead of duplicating this literal \"--scope\" 3 times.","severity":"Critical","line":199}]}