{"id":"0726a0a8-a74e-4eb8-9101-e2a0baa70818","startTime":"2021-01-24T14:03:42.48581","endTime":"2021-01-24T14:07:19.772659","productName":"/home/ubuntu/tests/storybook","totalLinesOfCode":150580,"isRunning":false,"isDiagnosticsFinished":true,"isFullAnalysisFinished":true,"durationSeconds":217,"remainingSeconds":null,"estimatedTotalTimeSeconds":null,"isConfirmed":false,"jobs":[{"name":"Tech Stack","startTime":"2021-01-24T14:03:42.689856","endTime":"2021-01-24T14:03:45.672713","status":"Success","statusText":"Scanned 2833 files","isRunning":false,"durationSeconds":2},{"name":"Hardcoded Analysis","startTime":"2021-01-24T14:03:48.257372","endTime":"2021-01-24T14:03:51.698477","status":"Success","statusText":"Detected 358 findings","isRunning":false,"durationSeconds":3},{"name":"Business Risks Analysis","startTime":"2021-01-24T14:07:19.459263","endTime":"2021-01-24T14:07:19.764273","status":"Success","statusText":"Business risks saved to DB: 7","isRunning":false,"durationSeconds":0},{"name":"License Compliance","startTime":"2021-01-24T14:06:02.359168","endTime":"2021-01-24T14:07:19.454122","status":"Success","statusText":"Detected 4 unique licenses","isRunning":false,"durationSeconds":77},{"name":"Tech Stack Filtering","startTime":"2021-01-24T14:03:47.741871","endTime":"2021-01-24T14:03:48.253265","status":"Success","statusText":"2627 files included, 206 skipped","isRunning":false,"durationSeconds":0},{"name":"Code Risks","startTime":"2021-01-24T14:03:45.700106","endTime":"2021-01-24T14:03:47.738016","status":"Success","statusText":"Processed 2833 files","isRunning":false,"durationSeconds":2},{"name":"Static Code Analysis","startTime":"2021-01-24T14:03:51.707197","endTime":"2021-01-24T14:06:02.35288","status":"Success","statusText":"Found 13 issues (0 bugs, 0 code smells, 13 vulnerabilities), Found 32 issues (4 bugs, 28 code smells, 0 vulnerabilities), 14 exported, Duplicated lines (total 2455) exported for 39 files.","isRunning":false,"durationSeconds":130}],"businessRisks":[{"category":"License Compliance","type":"License Compliance","grade":"Satisfactory","transcript":"0 reciprocal license risks, 6 total license risks"},{"category":"Code Quality","type":"Hardcoded Items","grade":"Excellent","transcript":"0.1% code lines (86 of 147459, 5.8 per 10K) contain hardcoded items"},{"category":"Security","type":"Security Hotspots","grade":"Excellent","transcript":"14 security hotspots (0.9 per 10K code lines)"},{"category":"Code Quality","type":"Defects","grade":"Excellent","transcript":"0.0% code lines (11 of 147459, 0.7 per 10K) contain major issues"},{"category":"Code Quality","type":"Code Smells","grade":"Excellent","transcript":"0.0% code lines (1 of 147459, 0.1 per 10K) contain blocker code smells"},{"category":"Security","type":"Vulnerabilities","grade":"Failed","transcript":"13 vulnerabilities (0.9 per 10K code lines)"},{"category":"Code Quality","type":"Duplications","grade":"Excellent","transcript":"1.7% code lines (2455 of 147459) are duplicated"}],"user":"cwt_default@example.com","repositories":[""]}