{"id":"58c884cb-b7a5-4171-adb6-53c7b04c55fe","startTime":"2021-01-15T14:16:28.184003","endTime":"2021-01-15T14:21:10.799862","productName":"firefox-ios","totalLinesOfCode":142961,"isRunning":false,"isDiagnosticsFinished":true,"isFullAnalysisFinished":true,"durationSeconds":282,"remainingSeconds":null,"estimatedTotalTimeSeconds":null,"isConfirmed":false,"jobs":[{"name":"License Compliance","startTime":"2021-01-15T14:18:33.416876","endTime":"2021-01-15T14:21:10.655599","status":"Success","statusText":"Detected 12 unique licenses","isRunning":false,"durationSeconds":157},{"name":"Code Risks","startTime":"2021-01-15T14:16:30.262772","endTime":"2021-01-15T14:16:31.444051","status":"Success","statusText":"Processed 1353 files","isRunning":false,"durationSeconds":1},{"name":"Static Code Analysis","startTime":"2021-01-15T14:16:34.733974","endTime":"2021-01-15T14:18:33.409837","status":"Success","statusText":"Found 0 issues (0 bugs, 0 code smells, 0 vulnerabilities), Found 136 issues (92 bugs, 44 code smells, 0 vulnerabilities), 12 exported, Duplicated lines (total 802) exported for 2 files.","isRunning":false,"durationSeconds":118},{"name":"Hardcoded Analysis","startTime":"2021-01-15T14:16:31.702645","endTime":"2021-01-15T14:16:34.724255","status":"Success","statusText":"Detected 413 findings","isRunning":false,"durationSeconds":3},{"name":"Business Risks Analysis","startTime":"2021-01-15T14:21:10.662246","endTime":"2021-01-15T14:21:10.787609","status":"Success","statusText":"Business risks saved to DB: 7","isRunning":false,"durationSeconds":0},{"name":"Tech Stack","startTime":"2021-01-15T14:16:28.392297","endTime":"2021-01-15T14:16:30.23893","status":"Success","statusText":"Scanned 1353 files","isRunning":false,"durationSeconds":1},{"name":"Tech Stack Filtering","startTime":"2021-01-15T14:16:31.448927","endTime":"2021-01-15T14:16:31.698372","status":"Success","statusText":"947 files included, 406 skipped","isRunning":false,"durationSeconds":0}],"businessRisks":[{"category":"Code Quality","type":"Hardcoded Items","grade":"Excellent","transcript":"0.2% code lines (196 of 122727, 16.0 per 10K) contain hardcoded items"},{"category":"Code Quality","type":"Code Smells","grade":"Excellent","transcript":"0.0% code lines (0 of 122727, 0.0 per 10K) contain blocker code smells"},{"category":"License Compliance","type":"License Compliance","grade":"Satisfactory","transcript":"3 reciprocal license risks, 963 total license risks"},{"category":"Security","type":"Security Hotspots","grade":"Excellent","transcript":"12 security hotspots (1.0 per 10K code lines)"},{"category":"Code Quality","type":"Defects","grade":"Excellent","transcript":"0.1% code lines (93 of 122727, 7.6 per 10K) contain major issues"},{"category":"Security","type":"Vulnerabilities","grade":"Excellent","transcript":"0 vulnerabilities (0.0 per 10K code lines)"},{"category":"Code Quality","type":"Duplications","grade":"Excellent","transcript":"0.7% code lines (802 of 122727) are duplicated"}],"user":"cwt_default@example.com","repositories":[""]}