{"id":"5d52d116-7027-4648-a6c7-30ea6efbfff7","startTime":"2020-11-04T13:23:31.3294492","endTime":"2020-11-04T13:30:58.5832966","productName":"ansible","totalLinesOfCode":286345,"isRunning":false,"isDiagnosticsFinished":true,"durationSeconds":447,"remainingSeconds":null,"estimatedTotalTimeSeconds":null,"isConfirmed":false,"techStacks":[{"language":"reStructuredText","files":350,"code":23299,"comments":15708,"blanks":16791,"testCoveragePercentage":null,"languageType":"Unknown"},{"language":"Bourne Shell","files":189,"code":3630,"comments":843,"blanks":1400,"testCoveragePercentage":null,"languageType":"Code"},{"language":"C#","files":12,"code":4058,"comments":256,"blanks":619,"testCoveragePercentage":null,"languageType":"Code"},{"language":"YAML","files":1533,"code":88888,"comments":3419,"blanks":7871,"testCoveragePercentage":null,"languageType":"Configuration"},{"language":"PowerShell","files":138,"code":16615,"comments":2156,"blanks":2996,"testCoveragePercentage":null,"languageType":"Code"},{"language":"TOML","files":3,"code":15,"comments":0,"blanks":1,"testCoveragePercentage":null,"languageType":"Code"},{"language":"CSS","files":4,"code":104,"comments":37,"blanks":1,"testCoveragePercentage":null,"languageType":"Markup"},{"language":"Fish Shell","files":1,"code":79,"comments":14,"blanks":16,"testCoveragePercentage":null,"languageType":"Code"},{"language":"make","files":6,"code":399,"comments":52,"blanks":85,"testCoveragePercentage":null,"languageType":"BuildScript"},{"language":"Markdown","files":54,"code":875,"comments":0,"blanks":475,"testCoveragePercentage":null,"languageType":"Markup"},{"language":"Dockerfile","files":1,"code":17,"comments":0,"blanks":3,"testCoveragePercentage":null,"languageType":"Code"},{"language":"JavaScript","files":4,"code":100,"comments":8,"blanks":10,"testCoveragePercentage":null,"languageType":"Code"},{"language":"Python","files":1303,"code":140958,"comments":69609,"blanks":42901,"testCoveragePercentage":null,"languageType":"Code"},{"language":"Windows Resource File","files":1,"code":13,"comments":0,"blanks":3,"testCoveragePercentage":null,"languageType":"Configuration"},{"language":"INI","files":16,"code":95,"comments":0,"blanks":29,"testCoveragePercentage":null,"languageType":"Configuration"},{"language":"XML","files":1,"code":34,"comments":0,"blanks":2,"testCoveragePercentage":null,"languageType":"Configuration"},{"language":"Bourne Again Shell","files":1,"code":28,"comments":7,"blanks":8,"testCoveragePercentage":null,"languageType":"Code"},{"language":"Go","files":1,"code":61,"comments":14,"blanks":14,"testCoveragePercentage":null,"languageType":"Code"},{"language":"DOS Batch","files":3,"code":5,"comments":0,"blanks":0,"testCoveragePercentage":null,"languageType":"Code"},{"language":"JSON","files":174,"code":3826,"comments":0,"blanks":3,"testCoveragePercentage":null,"languageType":"Configuration"},{"language":"HTML","files":15,"code":575,"comments":23,"blanks":54,"testCoveragePercentage":null,"languageType":"Markup"},{"language":"SVG","files":1,"code":2671,"comments":0,"blanks":0,"testCoveragePercentage":null,"languageType":"Unknown"}],"jobs":[{"name":"Code Risks","startTime":"2020-11-04T13:23:36.3625847","endTime":"2020-11-04T13:23:40.7213318","status":"Success","statusText":"Processed 3811 files","isRunning":false,"durationSeconds":4},{"name":"Hardcoded Analysis","startTime":"2020-11-04T13:23:41.5056184","endTime":"2020-11-04T13:24:20.7773541","status":"Success","statusText":"Detected 2232 findings","isRunning":false,"durationSeconds":39},{"name":"License Compliance","startTime":"2020-11-04T13:27:03.7759265","endTime":"2020-11-04T13:30:58.5507675","status":"Success","statusText":"Detected 17 unique licenses","isRunning":false,"durationSeconds":234},{"name":"Static Code Analysis","startTime":"2020-11-04T13:24:20.7980654","endTime":"2020-11-04T13:27:03.754187","status":"Success","statusText":"Found 1569 issues (46 bugs, 1513 code smells, 10 vulnerabilities), Duplicated lines exported for 48 files.","isRunning":false,"durationSeconds":162},{"name":"Tech Stack Filtering","startTime":"2020-11-04T13:23:40.7299407","endTime":"2020-11-04T13:23:41.4950184","status":"Success","statusText":"3265 files included, 546 skipped","isRunning":false,"durationSeconds":0},{"name":"Tech Stack","startTime":"2020-11-04T13:23:31.8156529","endTime":"2020-11-04T13:23:36.335821","status":"Success","statusText":"Scanned 3811 files","isRunning":false,"durationSeconds":4}]}