{"id":"793f51d4-dab3-4e00-93cb-809ff6178e38","startTime":"2021-02-06T20:07:58.200903","endTime":"2021-02-06T20:11:43.63991","productName":"storybook","totalLinesOfCode":153480,"isRunning":false,"isDiagnosticsFinished":true,"isFullAnalysisFinished":true,"durationSeconds":225,"remainingSeconds":null,"estimatedTotalTimeSeconds":null,"isConfirmed":false,"jobs":[{"name":"Code Risks","startTime":"2021-02-06T20:08:01.592022","endTime":"2021-02-06T20:08:03.659367","status":"Success","statusText":"Processed 2927 files","isRunning":false,"durationSeconds":2},{"name":"Static Code Analysis","startTime":"2021-02-06T20:08:07.342129","endTime":"2021-02-06T20:10:20.286639","status":"Success","statusText":"Found 26 issues (0 bugs, 0 code smells, 26 vulnerabilities), Found 115 issues (11 bugs, 104 code smells, 0 vulnerabilities), 14 exported, Duplicated lines (total 2641) exported for 43 files.","isRunning":false,"durationSeconds":132},{"name":"Tech Stack Filtering","startTime":"2021-02-06T20:08:03.662945","endTime":"2021-02-06T20:08:04.184987","status":"Success","statusText":"2714 files included, 213 skipped","isRunning":false,"durationSeconds":0},{"name":"Hardcoded Analysis","startTime":"2021-02-06T20:08:04.189823","endTime":"2021-02-06T20:08:07.33234","status":"Success","statusText":"Detected 377 findings","isRunning":false,"durationSeconds":3},{"name":"Tech Stack","startTime":"2021-02-06T20:07:58.408703","endTime":"2021-02-06T20:08:01.570204","status":"Success","statusText":"Scanned 2927 files","isRunning":false,"durationSeconds":3},{"name":"License Compliance","startTime":"2021-02-06T20:10:20.29427","endTime":"2021-02-06T20:11:42.8315","status":"Success","statusText":"Detected 4 unique licenses","isRunning":false,"durationSeconds":82},{"name":"Business Risks Analysis","startTime":"2021-02-06T20:11:42.837358","endTime":"2021-02-06T20:11:43.631816","status":"Success","statusText":"Business risks saved to DB: 7","isRunning":false,"durationSeconds":0}],"businessRisks":[{"category":"Code Quality","type":"Defects","grade":"Excellent","transcript":"0.0% code lines (11 of 150320, 0.7 per 10K) contain major issues"},{"category":"Code Quality","type":"Code Smells","grade":"Excellent","transcript":"0.0% code lines (1 of 150320, 0.1 per 10K) contain blocker code smells"},{"category":"Security","type":"Security Hotspots","grade":"Excellent","transcript":"14 security hotspots (0.9 per 10K code lines)"},{"category":"Security","type":"Vulnerabilities","grade":"Failed","transcript":"26 vulnerabilities (1.7 per 10K code lines)"},{"category":"Code Quality","type":"Hardcoded Items","grade":"Excellent","transcript":"0.1% code lines (90 of 150320, 6.0 per 10K) contain hardcoded items"},{"category":"Code Quality","type":"Duplications","grade":"Excellent","transcript":"1.8% code lines (2641 of 150320) are duplicated"},{"category":"License Compliance","type":"License Compliance","grade":"Satisfactory","transcript":"0 reciprocal license risks, 6 total license risks"}],"user":"cwt_default@example.com","repositories":[""]}