{"id":"7a10e4d5-84db-4af7-9cfd-5b2d29eb2b0a","startTime":"2021-01-15T14:12:00.781721","endTime":"2021-01-15T14:16:23.401066","productName":"gatsby","totalLinesOfCode":754495,"isRunning":false,"isDiagnosticsFinished":true,"isFullAnalysisFinished":true,"durationSeconds":262,"remainingSeconds":null,"estimatedTotalTimeSeconds":null,"isConfirmed":false,"jobs":[{"name":"Hardcoded Analysis","startTime":"2021-01-15T14:12:14.688492","endTime":"2021-01-15T14:12:19.90215","status":"Success","statusText":"Detected 1424 findings","isRunning":false,"durationSeconds":5},{"name":"License Compliance","startTime":"2021-01-15T14:14:39.885691","endTime":"2021-01-15T14:16:23.266575","status":"Success","statusText":"Detected 14 unique licenses","isRunning":false,"durationSeconds":103},{"name":"Static Code Analysis","startTime":"2021-01-15T14:12:19.91151","endTime":"2021-01-15T14:14:39.879395","status":"Success","statusText":"Found 0 issues (0 bugs, 0 code smells, 0 vulnerabilities), Found 376 issues (80 bugs, 296 code smells, 0 vulnerabilities), 19 exported, Duplicated lines (total 9288) exported for 184 files.","isRunning":false,"durationSeconds":139},{"name":"Tech Stack Filtering","startTime":"2021-01-15T14:12:14.174326","endTime":"2021-01-15T14:12:14.677047","status":"Success","statusText":"2277 files included, 2178 skipped","isRunning":false,"durationSeconds":0},{"name":"Code Risks","startTime":"2021-01-15T14:12:11.163444","endTime":"2021-01-15T14:12:14.164131","status":"Success","statusText":"Processed 4455 files","isRunning":false,"durationSeconds":3},{"name":"Business Risks Analysis","startTime":"2021-01-15T14:16:23.271994","endTime":"2021-01-15T14:16:23.391374","status":"Success","statusText":"Business risks saved to DB: 7","isRunning":false,"durationSeconds":0},{"name":"Tech Stack","startTime":"2021-01-15T14:12:00.995925","endTime":"2021-01-15T14:12:11.143303","status":"Success","statusText":"Scanned 4455 files","isRunning":false,"durationSeconds":10}],"businessRisks":[{"category":"Security","type":"Security Hotspots","grade":"Excellent","transcript":"19 security hotspots (0.8 per 10K code lines)"},{"category":"Security","type":"Vulnerabilities","grade":"Excellent","transcript":"0 vulnerabilities (0.0 per 10K code lines)"},{"category":"License Compliance","type":"License Compliance","grade":"Satisfactory","transcript":"0 reciprocal license risks, 81 total license risks"},{"category":"Code Quality","type":"Code Smells","grade":"Excellent","transcript":"0.0% code lines (0 of 240858, 0.0 per 10K) contain blocker code smells"},{"category":"Code Quality","type":"Hardcoded Items","grade":"Excellent","transcript":"0.0% code lines (119 of 240858, 4.9 per 10K) contain hardcoded items"},{"category":"Code Quality","type":"Duplications","grade":"Satisfactory","transcript":"3.9% code lines (9288 of 240858) are duplicated"},{"category":"Code Quality","type":"Defects","grade":"Excellent","transcript":"0.0% code lines (118 of 240858, 4.9 per 10K) contain major issues"}],"user":"cwt_default@example.com","repositories":[""]}