{"id":"82982393-3a95-425d-83a0-2727368234a9","startTime":"2021-02-05T20:19:34.688045","endTime":"2021-02-05T20:24:14.315071","productName":"firefox-ios","totalLinesOfCode":142435,"isRunning":false,"isDiagnosticsFinished":true,"isFullAnalysisFinished":true,"durationSeconds":279,"remainingSeconds":null,"estimatedTotalTimeSeconds":null,"isConfirmed":false,"jobs":[{"name":"Tech Stack","startTime":"2021-02-05T20:19:34.961491","endTime":"2021-02-05T20:19:36.872811","status":"Success","statusText":"Scanned 1354 files","isRunning":false,"durationSeconds":1},{"name":"Code Risks","startTime":"2021-02-05T20:19:36.896977","endTime":"2021-02-05T20:19:38.144457","status":"Success","statusText":"Processed 1354 files","isRunning":false,"durationSeconds":1},{"name":"Hardcoded Analysis","startTime":"2021-02-05T20:19:38.385239","endTime":"2021-02-05T20:19:41.403239","status":"Success","statusText":"Detected 412 findings","isRunning":false,"durationSeconds":3},{"name":"Tech Stack Filtering","startTime":"2021-02-05T20:19:38.148213","endTime":"2021-02-05T20:19:38.380353","status":"Success","statusText":"948 files included, 406 skipped","isRunning":false,"durationSeconds":0},{"name":"Static Code Analysis","startTime":"2021-02-05T20:19:41.412827","endTime":"2021-02-05T20:21:39.598485","status":"Success","statusText":"Found 0 issues (0 bugs, 0 code smells, 0 vulnerabilities), Found 166 issues (93 bugs, 73 code smells, 0 vulnerabilities), 12 exported, Duplicated lines (total 802) exported for 2 files.","isRunning":false,"durationSeconds":118},{"name":"License Compliance","startTime":"2021-02-05T20:21:39.604772","endTime":"2021-02-05T20:24:13.588715","status":"Success","statusText":"Detected 12 unique licenses","isRunning":false,"durationSeconds":153},{"name":"Business Risks Analysis","startTime":"2021-02-05T20:24:13.595585","endTime":"2021-02-05T20:24:14.306827","status":"Success","statusText":"Business risks saved to DB: 7","isRunning":false,"durationSeconds":0}],"businessRisks":[{"category":"Code Quality","type":"Duplications","grade":"Excellent","transcript":"0.7% code lines (802 of 122208) are duplicated"},{"category":"Security","type":"Security Hotspots","grade":"Excellent","transcript":"12 security hotspots (1.0 per 10K code lines)"},{"category":"Security","type":"Vulnerabilities","grade":"Excellent","transcript":"0 vulnerabilities (0.0 per 10K code lines)"},{"category":"Code Quality","type":"Defects","grade":"Excellent","transcript":"0.1% code lines (93 of 122208, 7.6 per 10K) contain major issues"},{"category":"License Compliance","type":"License Compliance","grade":"Satisfactory","transcript":"3 reciprocal license risks, 963 total license risks"},{"category":"Code Quality","type":"Hardcoded Items","grade":"Excellent","transcript":"0.2% code lines (197 of 122208, 16.1 per 10K) contain hardcoded items"},{"category":"Code Quality","type":"Code Smells","grade":"Excellent","transcript":"0.0% code lines (0 of 122208, 0.0 per 10K) contain blocker code smells"}],"user":"cwt_default@example.com","repositories":[""]}