{"id":"9dbb592c-3cbd-4e38-89f5-e3a3d7ac9597","startTime":"2021-02-08T00:32:47.364208","endTime":"2021-02-08T01:14:01.259451","productName":"kubernetes","totalLinesOfCode":4538741,"isRunning":false,"isDiagnosticsFinished":true,"isFullAnalysisFinished":true,"durationSeconds":2473,"remainingSeconds":null,"estimatedTotalTimeSeconds":null,"isConfirmed":false,"jobs":[{"name":"Business Risks Analysis","startTime":"2021-02-08T01:14:00.360008","endTime":"2021-02-08T01:14:01.251575","status":"Success","statusText":"Business risks saved to DB: 7","isRunning":false,"durationSeconds":0},{"name":"Static Code Analysis","startTime":"2021-02-08T00:34:30.776982","endTime":"2021-02-08T00:41:12.408165","status":"Success","statusText":"Found 5056 issues (0 bugs, 0 code smells, 5056 vulnerabilities), Found 11478 issues (23 bugs, 11455 code smells, 0 vulnerabilities), 8 exported, Duplicated lines (total 219578) exported for 1651 files.","isRunning":false,"durationSeconds":401},{"name":"Code Risks","startTime":"2021-02-08T00:33:34.856404","endTime":"2021-02-08T00:33:45.413018","status":"Success","statusText":"Processed 20391 files","isRunning":false,"durationSeconds":10},{"name":"Tech Stack","startTime":"2021-02-08T00:32:47.572022","endTime":"2021-02-08T00:33:34.837286","status":"Success","statusText":"Scanned 20391 files","isRunning":false,"durationSeconds":47},{"name":"Hardcoded Analysis","startTime":"2021-02-08T00:33:47.931407","endTime":"2021-02-08T00:34:30.766383","status":"Success","statusText":"Detected 14713 findings","isRunning":false,"durationSeconds":42},{"name":"Tech Stack Filtering","startTime":"2021-02-08T00:33:45.416671","endTime":"2021-02-08T00:33:47.927634","status":"Success","statusText":"11855 files included, 8536 skipped","isRunning":false,"durationSeconds":2},{"name":"License Compliance","startTime":"2021-02-08T00:41:12.414736","endTime":"2021-02-08T01:14:00.349663","status":"Success","statusText":"Detected 9 unique licenses","isRunning":false,"durationSeconds":1967}],"businessRisks":[{"category":"Code Quality","type":"Duplications","grade":"Failed","transcript":"10.5% code lines (219578 of 2091416) are duplicated"},{"category":"Security","type":"Vulnerabilities","grade":"Failed","transcript":"5056 vulnerabilities (24.2 per 10K code lines)"},{"category":"License Compliance","type":"License Compliance","grade":"Satisfactory","transcript":"0 reciprocal license risks, 87 total license risks"},{"category":"Code Quality","type":"Defects","grade":"Excellent","transcript":"0.0% code lines (220 of 2091416, 1.1 per 10K) contain major issues"},{"category":"Code Quality","type":"Code Smells","grade":"Excellent","transcript":"0.0% code lines (0 of 2091416, 0.0 per 10K) contain blocker code smells"},{"category":"Code Quality","type":"Hardcoded Items","grade":"Excellent","transcript":"0.2% code lines (3696 of 2091416, 17.7 per 10K) contain hardcoded items"},{"category":"Security","type":"Security Hotspots","grade":"Excellent","transcript":"8 security hotspots (0.0 per 10K code lines)"}],"user":"cwt_default@example.com","repositories":[""]}