{"id":"a68537d8-c481-497a-b03d-a7cd192c59db","startTime":"2021-02-04T02:28:57.774975","endTime":"2021-02-04T02:33:31.765961","productName":"azure-devops-docs","totalLinesOfCode":314351,"isRunning":false,"isDiagnosticsFinished":true,"isFullAnalysisFinished":true,"durationSeconds":273,"remainingSeconds":null,"estimatedTotalTimeSeconds":null,"isConfirmed":false,"jobs":[{"name":"Business Risks Analysis","startTime":"2021-02-04T02:33:31.215238","endTime":"2021-02-04T02:33:31.757739","status":"Success","statusText":"Business risks saved to DB: 7","isRunning":false,"durationSeconds":0},{"name":"Hardcoded Analysis","startTime":"2021-02-04T02:29:04.354819","endTime":"2021-02-04T02:29:08.230053","status":"Success","statusText":"Detected 2022 findings","isRunning":false,"durationSeconds":3},{"name":"Tech Stack Filtering","startTime":"2021-02-04T02:29:03.723015","endTime":"2021-02-04T02:29:04.350647","status":"Success","statusText":"3099 files included, 163 skipped","isRunning":false,"durationSeconds":0},{"name":"License Compliance","startTime":"2021-02-04T02:30:41.128825","endTime":"2021-02-04T02:33:31.210027","status":"Success","statusText":"Detected 8 unique licenses","isRunning":false,"durationSeconds":170},{"name":"Tech Stack","startTime":"2021-02-04T02:28:58.07683","endTime":"2021-02-04T02:29:01.302465","status":"Success","statusText":"Scanned 3262 files","isRunning":false,"durationSeconds":3},{"name":"Static Code Analysis","startTime":"2021-02-04T02:29:08.240487","endTime":"2021-02-04T02:30:41.12212","status":"Success","statusText":"Found 0 issues (0 bugs, 0 code smells, 0 vulnerabilities), Found 0 issues (0 bugs, 0 code smells, 0 vulnerabilities), 0 exported, Duplicated lines (total 0) exported for 0 files.","isRunning":false,"durationSeconds":92},{"name":"Code Risks","startTime":"2021-02-04T02:29:01.322332","endTime":"2021-02-04T02:29:03.71913","status":"Success","statusText":"Processed 3262 files","isRunning":false,"durationSeconds":2}],"businessRisks":[{"category":"Code Quality","type":"Defects","grade":"Excellent","transcript":"0.0% code lines (0 of 303019, 0.0 per 10K) contain major issues"},{"category":"Code Quality","type":"Hardcoded Items","grade":"Excellent","transcript":"0.0% code lines (1 of 303019, 0.0 per 10K) contain hardcoded items"},{"category":"Code Quality","type":"Code Smells","grade":"Excellent","transcript":"0.0% code lines (0 of 303019, 0.0 per 10K) contain blocker code smells"},{"category":"Security","type":"Security Hotspots","grade":"Excellent","transcript":"0 security hotspots (0.0 per 10K code lines)"},{"category":"License Compliance","type":"License Compliance","grade":"Satisfactory","transcript":"0 reciprocal license risks, 405 total license risks"},{"category":"Code Quality","type":"Duplications","grade":"Excellent","transcript":"0.0% code lines (0 of 303019) are duplicated"},{"category":"Security","type":"Vulnerabilities","grade":"Excellent","transcript":"0 vulnerabilities (0.0 per 10K code lines)"}],"user":"cwt_default@example.com","repositories":[""]}