{"id":"b848e0f6-1ed4-4387-ac5c-c305c79a785a","startTime":"2020-10-31T15:32:41.6869515","endTime":"2020-10-31T15:42:36.641826","productName":"istio","totalLinesOfCode":401471,"isRunning":false,"isDiagnosticsFinished":true,"durationSeconds":594,"remainingSeconds":null,"estimatedTotalTimeSeconds":null,"isConfirmed":false,"techStacks":[{"language":"Go","files":1439,"code":250128,"comments":39753,"blanks":33638,"testCoveragePercentage":null,"languageType":"Code"},{"language":"XML","files":3,"code":30,"comments":22,"blanks":14,"testCoveragePercentage":null,"languageType":"Configuration"},{"language":"Gradle","files":4,"code":41,"comments":0,"blanks":8,"testCoveragePercentage":null,"languageType":"BuildScript"},{"language":"Protocol Buffers","files":157,"code":8742,"comments":20205,"blanks":5237,"testCoveragePercentage":null,"languageType":"Configuration"},{"language":"YAML","files":823,"code":87269,"comments":3744,"blanks":1336,"testCoveragePercentage":null,"languageType":"Configuration"},{"language":"Dockerfile","files":10,"code":95,"comments":124,"blanks":44,"testCoveragePercentage":null,"languageType":"Code"},{"language":"diff","files":29,"code":58,"comments":3131,"blanks":0,"testCoveragePercentage":null,"languageType":"Markup"},{"language":"Bourne Shell","files":62,"code":2861,"comments":1370,"blanks":694,"testCoveragePercentage":null,"languageType":"Code"},{"language":"SVG","files":4,"code":291,"comments":0,"blanks":0,"testCoveragePercentage":null,"languageType":"Unknown"},{"language":"Markdown","files":63,"code":3483,"comments":0,"blanks":1245,"testCoveragePercentage":null,"languageType":"Markup"},{"language":"SQL","files":1,"code":11,"comments":0,"blanks":2,"testCoveragePercentage":null,"languageType":"Code"},{"language":"JSON","files":48,"code":33105,"comments":0,"blanks":160,"testCoveragePercentage":null,"languageType":"Configuration"},{"language":"Ruby","files":2,"code":125,"comments":44,"blanks":32,"testCoveragePercentage":null,"languageType":"Code"},{"language":"HTML","files":5,"code":4136,"comments":58,"blanks":343,"testCoveragePercentage":null,"languageType":"Markup"},{"language":"Java","files":6,"code":190,"comments":100,"blanks":38,"testCoveragePercentage":null,"languageType":"Code"},{"language":"CSS","files":4,"code":7368,"comments":22,"blanks":7,"testCoveragePercentage":null,"languageType":"Markup"},{"language":"Python","files":6,"code":563,"comments":206,"blanks":178,"testCoveragePercentage":null,"languageType":"Code"},{"language":"JavaScript","files":5,"code":1809,"comments":229,"blanks":605,"testCoveragePercentage":null,"languageType":"Code"},{"language":"make","files":14,"code":1166,"comments":396,"blanks":349,"testCoveragePercentage":null,"languageType":"BuildScript"}],"jobs":[{"name":"Static Code Analysis","startTime":"2020-10-31T15:33:02.2923087","endTime":"2020-10-31T15:35:53.0767539","status":"Success","statusText":"Found 2083 issues (216 bugs, 1867 code smells, 0 vulnerabilities), Duplicated lines exported for 185 files.","isRunning":false,"durationSeconds":170},{"name":"License Compliance","startTime":"2020-10-31T15:35:53.0978082","endTime":"2020-10-31T15:42:36.611061","status":"Success","statusText":"Detected 13 unique licenses","isRunning":false,"durationSeconds":403},{"name":"Code Analysis (Internal)","startTime":"2020-10-31T15:32:50.7808122","endTime":"2020-10-31T15:32:51.0244372","status":"Success","statusText":"","isRunning":false,"durationSeconds":0},{"name":"Hardcoded Analysis","startTime":"2020-10-31T15:32:51.0325312","endTime":"2020-10-31T15:33:02.2717607","status":"Success","statusText":"Detected 923 findings","isRunning":false,"durationSeconds":11},{"name":"Tech Stack","startTime":"2020-10-31T15:32:42.0676942","endTime":"2020-10-31T15:32:46.9982942","status":"Success","statusText":"Scanned 2685 files","isRunning":false,"durationSeconds":4},{"name":"Tech Stack Filtering","startTime":"2020-10-31T15:32:50.1571513","endTime":"2020-10-31T15:32:50.7723427","status":"Success","statusText":"2422 files included, 263 skipped","isRunning":false,"durationSeconds":0},{"name":"Code Risks","startTime":"2020-10-31T15:32:47.0415558","endTime":"2020-10-31T15:32:50.1477082","status":"Success","statusText":"Processed 2685 files","isRunning":false,"durationSeconds":3}]}