{"id":"bc9bcca3-2d79-45d9-89d5-966f94ea0966","startTime":"2021-01-25T02:23:43.902863","endTime":"2021-01-25T02:28:17.07372","productName":"/home/ubuntu/tests/azure-devops-docs","totalLinesOfCode":315665,"isRunning":false,"isDiagnosticsFinished":true,"isFullAnalysisFinished":true,"durationSeconds":273,"remainingSeconds":null,"estimatedTotalTimeSeconds":null,"isConfirmed":false,"jobs":[{"name":"Business Risks Analysis","startTime":"2021-01-25T02:28:16.745621","endTime":"2021-01-25T02:28:17.064634","status":"Success","statusText":"Business risks saved to DB: 7","isRunning":false,"durationSeconds":0},{"name":"Code Risks","startTime":"2021-01-25T02:23:47.208414","endTime":"2021-01-25T02:23:49.498773","status":"Success","statusText":"Processed 3266 files","isRunning":false,"durationSeconds":2},{"name":"Static Code Analysis","startTime":"2021-01-25T02:23:53.911218","endTime":"2021-01-25T02:25:27.367813","status":"Success","statusText":"Found 0 issues (0 bugs, 0 code smells, 0 vulnerabilities), Found 0 issues (0 bugs, 0 code smells, 0 vulnerabilities), 0 exported, Duplicated lines (total 0) exported for 0 files.","isRunning":false,"durationSeconds":93},{"name":"License Compliance","startTime":"2021-01-25T02:25:27.373814","endTime":"2021-01-25T02:28:16.73865","status":"Success","statusText":"Detected 9 unique licenses","isRunning":false,"durationSeconds":169},{"name":"Tech Stack","startTime":"2021-01-25T02:23:44.107964","endTime":"2021-01-25T02:23:47.18849","status":"Success","statusText":"Scanned 3266 files","isRunning":false,"durationSeconds":3},{"name":"Hardcoded Analysis","startTime":"2021-01-25T02:23:50.130305","endTime":"2021-01-25T02:23:53.902469","status":"Success","statusText":"Detected 2069 findings","isRunning":false,"durationSeconds":3},{"name":"Tech Stack Filtering","startTime":"2021-01-25T02:23:49.502847","endTime":"2021-01-25T02:23:50.124145","status":"Success","statusText":"3103 files included, 163 skipped","isRunning":false,"durationSeconds":0}],"businessRisks":[{"category":"License Compliance","type":"License Compliance","grade":"Satisfactory","transcript":"0 reciprocal license risks, 414 total license risks"},{"category":"Code Quality","type":"Code Smells","grade":"Excellent","transcript":"0.0% code lines (0 of 304333, 0.0 per 10K) contain blocker code smells"},{"category":"Security","type":"Vulnerabilities","grade":"Excellent","transcript":"0 vulnerabilities (0.0 per 10K code lines)"},{"category":"Security","type":"Security Hotspots","grade":"Excellent","transcript":"0 security hotspots (0.0 per 10K code lines)"},{"category":"Code Quality","type":"Duplications","grade":"Excellent","transcript":"0.0% code lines (0 of 304333) are duplicated"},{"category":"Code Quality","type":"Defects","grade":"Excellent","transcript":"0.0% code lines (0 of 304333, 0.0 per 10K) contain major issues"},{"category":"Code Quality","type":"Hardcoded Items","grade":"Excellent","transcript":"0.0% code lines (1 of 304333, 0.0 per 10K) contain hardcoded items"}],"user":"cwt_default@example.com","repositories":[""]}