{"id":"f9751253-3153-496e-a4b1-1d237e79655e","startTime":"2020-11-05T08:16:06.5664667","endTime":"2020-11-05T08:20:22.0900953","productName":"charts","totalLinesOfCode":302346,"isRunning":false,"isDiagnosticsFinished":true,"durationSeconds":255,"remainingSeconds":null,"estimatedTotalTimeSeconds":null,"isConfirmed":false,"techStacks":[{"language":"JSON","files":13,"code":1868,"comments":0,"blanks":0,"testCoveragePercentage":null,"languageType":"Configuration"},{"language":"Markdown","files":394,"code":45953,"comments":0,"blanks":14458,"testCoveragePercentage":null,"languageType":"Markup"},{"language":"YAML","files":4077,"code":252332,"comments":39401,"blanks":13167,"testCoveragePercentage":null,"languageType":"Configuration"},{"language":"Dockerfile","files":5,"code":45,"comments":54,"blanks":22,"testCoveragePercentage":null,"languageType":"Code"},{"language":"Python","files":4,"code":480,"comments":89,"blanks":121,"testCoveragePercentage":null,"languageType":"Code"},{"language":"HTML","files":1,"code":1,"comments":0,"blanks":0,"testCoveragePercentage":null,"languageType":"Markup"},{"language":"make","files":2,"code":19,"comments":26,"blanks":10,"testCoveragePercentage":null,"languageType":"BuildScript"},{"language":"Go","files":2,"code":262,"comments":19,"blanks":50,"testCoveragePercentage":null,"languageType":"Code"},{"language":"XML","files":1,"code":43,"comments":9,"blanks":1,"testCoveragePercentage":null,"languageType":"Configuration"},{"language":"Bourne Shell","files":26,"code":1333,"comments":211,"blanks":330,"testCoveragePercentage":null,"languageType":"Code"},{"language":"Bourne Again Shell","files":1,"code":10,"comments":0,"blanks":1,"testCoveragePercentage":null,"languageType":"Code"}],"jobs":[{"name":"Hardcoded Analysis","startTime":"2020-11-05T08:16:16.3114587","endTime":"2020-11-05T08:16:24.7301061","status":"Success","statusText":"Detected 4232 findings","isRunning":false,"durationSeconds":8},{"name":"Tech Stack Filtering","startTime":"2020-11-05T08:16:15.2914437","endTime":"2020-11-05T08:16:16.3012906","status":"Success","statusText":"4523 files included, 3 skipped","isRunning":false,"durationSeconds":1},{"name":"Static Code Analysis","startTime":"2020-11-05T08:16:24.7489139","endTime":"2020-11-05T08:17:57.3686374","status":"Success","statusText":"Found 16 issues (1 bugs, 15 code smells, 0 vulnerabilities), Duplicated lines exported for 0 files.","isRunning":false,"durationSeconds":92},{"name":"Code Risks","startTime":"2020-11-05T08:16:10.7179698","endTime":"2020-11-05T08:16:15.2820084","status":"Success","statusText":"Processed 4526 files","isRunning":false,"durationSeconds":4},{"name":"Tech Stack","startTime":"2020-11-05T08:16:07.0526531","endTime":"2020-11-05T08:16:10.6842905","status":"Success","statusText":"Scanned 4526 files","isRunning":false,"durationSeconds":3},{"name":"License Compliance","startTime":"2020-11-05T08:17:57.3873975","endTime":"2020-11-05T08:20:22.0351208","status":"Success","statusText":"Detected 9 unique licenses","isRunning":false,"durationSeconds":144}]}