{"items":[{"id":null,"licenseName":"Apache-2.0","licenseLongName":"Apache License 2.0","licenseTextUrl":"https://spdx.org/licenses/Apache-2.0.html","fileName":"stable/rethinkdb/init/files/run.sh","risk":"","allowsSaas":"True","allowsDistribution":"True","allowsModification":"True"},{"id":null,"licenseName":"See-URL","licenseLongName":"","licenseTextUrl":"","fileName":"incubator/consul/README.md","risk":"","allowsSaas":"Uncertain","allowsDistribution":"Uncertain","allowsModification":"Uncertain"},{"id":null,"licenseName":"See-file","licenseLongName":"","licenseTextUrl":"","fileName":"stable/spring-cloud-data-flow/Chart.yaml","risk":"","allowsSaas":"Uncertain","allowsDistribution":"Uncertain","allowsModification":"Uncertain"},{"id":null,"licenseName":"See-doc.OTHER","licenseLongName":"","licenseTextUrl":"","fileName":"stable/couchdb/README.md","risk":"","allowsSaas":"Uncertain","allowsDistribution":"Uncertain","allowsModification":"Uncertain"},{"id":null,"licenseName":"UnclassifiedLicense","licenseLongName":"","licenseTextUrl":"","fileName":"CONTRIBUTING.md","risk":"","allowsSaas":"Uncertain","allowsDistribution":"Uncertain","allowsModification":"Uncertain"},{"id":null,"licenseName":"Apache-possibility","licenseLongName":"","licenseTextUrl":"","fileName":"stable/ignite/Chart.yaml","risk":"","allowsSaas":"Uncertain","allowsDistribution":"Uncertain","allowsModification":"Uncertain"},{"id":null,"licenseName":"Public-domain","licenseLongName":"","licenseTextUrl":"","fileName":"stable/rabbitmq-ha/README.md","risk":"","allowsSaas":"Uncertain","allowsDistribution":"Uncertain","allowsModification":"Uncertain"},{"id":null,"licenseName":"MIT","licenseLongName":"MIT License","licenseTextUrl":"https://spdx.org/licenses/MIT.html#licenseText","fileName":"stable/cerebro/README.md","risk":"","allowsSaas":"True","allowsDistribution":"True","allowsModification":"True"},{"id":null,"licenseName":"NOASSERTION","licenseLongName":"","licenseTextUrl":"","fileName":"stable/mssql-linux/README.md","risk":"","allowsSaas":"Uncertain","allowsDistribution":"Uncertain","allowsModification":"Uncertain"}],"paging":null}